NetoraPy/__init__.py
NetoraPy/NetoraTube/NetoraTube.py
NetoraPy/NetoraTube/__init__.py
NetoraPy/NetoraTube/app.py
netora_python-0.1.9.dist-info/METADATA
netora_python-0.1.9.dist-info/WHEEL
netora_python-0.1.9.dist-info/top_level.txt
netora_python-0.1.9.dist-info/RECORD
